<?xml version="1.0" encoding="utf-8"?>
<?xml-stylesheet type='text/xsl' href='C:\ProgramData\Windows App Certification Kit\results.xsl'?>
<REPORT xml:lang="fr-FR" OVERALL_RESULT="WARNING" VERSION="10.0.26100.7705" LATEST_VERSION="TRUE" UPDATE_DOWNLOAD_URL="" TOOLSET_ARCHITECTURE="x64" SecureBoot="FALSE" APP_TYPE="Centennial" PUBLISHER_DISPLAY_NAME="" APP_NAME="" APP_VERSION="" OSVERSION="10.0.26200.0" OS="Microsoft Windows 11 Famille" PER_USER_APPLICATION="" PARTIAL_RUN="FALSE" LCID="1036" X64_ONLY="FALSE" VALIDATION_TYPE="UI" ReportGenerationTime="05/05/2026 23:06:48" ID="1337cec05c0e42f47c36df4ebc04935e">
  <REQUIREMENTS>
    <REQUIREMENT NUMBER="3" TITLE="Test de signature numérique de fichiers" RATIONALE="Une signature numérique Authenticode garantit l’authenticité du logiciel aux utilisateurs. Cette signature permet également de détecter l’éventuelle falsification d’un fichier, par exemple s’il est infecté par un virus.">
      <TEST INDEX="2" NAME="Installer les pilotes signés et les fichiers exécutables" DESCRIPTION="Installer les pilotes signés et les fichiers exécutables." EXECUTIONTIME="00h:00m:00s.95ms" OPTIONAL="TRUE">
        <MESSAGES />
        <RESULT><![CDATA[PASS]]></RESULT>
      </TEST>
    </REQUIREMENT>
    <REQUIREMENT NUMBER="6" TITLE="Test de contrôle de compte utilisateur (UAC)" RATIONALE="La plupart des applications ne nécessitent pas de privilèges d’administrateur lors de l’exécution et s’exécutent généralement très bien avec un compte d’utilisateur standard. Les applications Windows ont besoin d’un fichier manifeste (intégré ou externe) qui définit leur niveau d’exécution et indique au système d’exploitation les privilèges nécessaires à leur exécution.">
      <TEST INDEX="11" NAME="Niveau d'exécution Contrôle de compte d'utilisateur" DESCRIPTION="Les applications Windows® ont besoin d’un fichier manifeste (intégré ou externe) qui définit leur niveau d’exécution et indique au système d’exploitation les privilèges nécessaires à leur exécution." EXECUTIONTIME="00h:00m:00s.79ms" OPTIONAL="TRUE">
        <MESSAGES />
        <RESULT><![CDATA[PASS]]></RESULT>
      </TEST>
    </REQUIREMENT>
    <REQUIREMENT NUMBER="12" TITLE="Test de conformité du package" RATIONALE="Le package ne respecte pas les règles de conformité du Microsoft Store.">
      <TEST INDEX="77" NAME="Nombre d'applications" DESCRIPTION="Un package ne doit pas définir plus d'une application dans le manifeste." EXECUTIONTIME="00h:00m:00s.87ms" OPTIONAL="TRUE">
        <MESSAGES />
        <RESULT><![CDATA[PASS]]></RESULT>
      </TEST>
      <TEST INDEX="31" NAME="Manifeste de l'application" DESCRIPTION="Le manifeste de l’application doit inclure des entrées valides pour tous les champs requis." EXECUTIONTIME="00h:00m:00s.95ms" OPTIONAL="FALSE">
        <MESSAGES />
        <RESULT><![CDATA[PASS]]></RESULT>
      </TEST>
      <TEST INDEX="87" NAME="Verbes d'association de fichier" DESCRIPTION="La validation du Registre a détecté qu'aucun verbe d'association de fichier enregistré n'est installé." EXECUTIONTIME="00h:00m:00s.92ms" OPTIONAL="TRUE">
        <MESSAGES />
        <RESULT><![CDATA[PASS]]></RESULT>
      </TEST>
      <TEST INDEX="86" NAME="Vérification du Registre" DESCRIPTION="La validation du Registre a détecté que des pilotes et que les services NT ne sont pas installés." EXECUTIONTIME="00h:00m:00s.82ms" OPTIONAL="TRUE">
        <MESSAGES />
        <RESULT><![CDATA[PASS]]></RESULT>
      </TEST>
      <TEST INDEX="91" NAME="Fonctionnalités d’entreprise" DESCRIPTION="Vérifiez si le package contient des fonctionnalités d’entreprise uniquement." EXECUTIONTIME="00h:00m:00s.84ms" OPTIONAL="FALSE">
        <MESSAGES />
        <RESULT><![CDATA[PASS]]></RESULT>
      </TEST>
      <TEST INDEX="90" NAME="Packages de ressources" DESCRIPTION="Vérifiez si des packages de ressources contiennent des fichiers PE." EXECUTIONTIME="00h:00m:00s.81ms" OPTIONAL="FALSE">
        <MESSAGES />
        <RESULT><![CDATA[PASS]]></RESULT>
      </TEST>
    </REQUIREMENT>
    <REQUIREMENT NUMBER="14" TITLE="Test des fonctionnalités de sécurité Windows" RATIONALE="Les applications doivent respecter les fonctionnalités de sécurité de Windows.">
      <TEST INDEX="70" NAME="Analyseur de fichiers non autorisés" DESCRIPTION="Analyse de l’application pour détecter des fichiers non sécurisés connus" EXECUTIONTIME="00h:00m:00s.75ms" OPTIONAL="FALSE">
        <MESSAGES />
        <RESULT><![CDATA[PASS]]></RESULT>
      </TEST>
      <TEST INDEX="62" NAME="Signature de code privé" DESCRIPTION="L'application ne doit pas créer un package contenant des fichiers de clés de signature de code." EXECUTIONTIME="00h:00m:00s.86ms" OPTIONAL="FALSE">
        <MESSAGES />
        <RESULT><![CDATA[PASS]]></RESULT>
      </TEST>
    </REQUIREMENT>
    <REQUIREMENT NUMBER="19" TITLE="Tests des ressources du manifeste de l'application" RATIONALE="Les ressources valides doivent être définies dans le fichier resources.pri du manifeste du package AppX, selon les Spécifications de la création du package AppX et du Schéma du manifeste AppX.">
      <TEST INDEX="45" NAME="Ressources de l'application" DESCRIPTION="Les ressources valides doivent être définies dans le fichier resources.pri du package." EXECUTIONTIME="00h:00m:00s.82ms" OPTIONAL="TRUE">
        <MESSAGES />
        <RESULT><![CDATA[PASS]]></RESULT>
      </TEST>
      <TEST INDEX="61" NAME="Personnalisation" DESCRIPTION="L'application ne doit pas utiliser les images par défaut fournies par les échantillons Windows SDK ou Visual Studio." EXECUTIONTIME="00h:00m:01s.04ms" OPTIONAL="FALSE">
        <MESSAGES />
        <RESULT><![CDATA[PASS]]></RESULT>
      </TEST>
    </REQUIREMENT>
    <REQUIREMENT NUMBER="20" TITLE="Test de configuration de débogage" RATIONALE="L’application ne doit pas installer de binaires de débogage.">
      <TEST INDEX="46" NAME="Configuration de débogage" DESCRIPTION="L’application ne doit pas installer de binaires de débogage." EXECUTIONTIME="00h:00m:00s.89ms" OPTIONAL="TRUE">
        <MESSAGES />
        <RESULT><![CDATA[PASS]]></RESULT>
      </TEST>
    </REQUIREMENT>
    <REQUIREMENT NUMBER="23" TITLE="Test des capacités des applications" RATIONALE="Les packages déclarant des capacités d'utilisation spéciales devront fournir des justifications au cours du processus d'intégration.">
      <TEST INDEX="52" NAME="Capacités d'utilisation spéciales" DESCRIPTION="Les packages déclarant des capacités d'utilisation spéciales devront fournir des justifications au cours du processus d'intégration." EXECUTIONTIME="00h:00m:00s.84ms" OPTIONAL="FALSE">
        <MESSAGES />
        <RESULT><![CDATA[PASS]]></RESULT>
      </TEST>
    </REQUIREMENT>
    <REQUIREMENT NUMBER="24" TITLE="Validation des métadonnées Windows Runtime" RATIONALE="Les métadonnées doivent être conformes et cohérentes dans toutes les sources de génération.">
      <TEST INDEX="56" NAME="Attribut ExclusiveTo" DESCRIPTION="Une classe ne doit pas implémenter une interface marquée comme ExclusiveTo d'une autre classe." EXECUTIONTIME="00h:00m:10s.17ms" OPTIONAL="FALSE">
        <MESSAGES />
        <RESULT><![CDATA[PASS]]></RESULT>
      </TEST>
      <TEST INDEX="57" NAME="Emplacement du type" DESCRIPTION="Les types doivent être définis dans le fichier de métadonnées ayant l'espace de noms le plus long correspondant." EXECUTIONTIME="00h:00m:01s.07ms" OPTIONAL="FALSE">
        <MESSAGES />
        <RESULT><![CDATA[PASS]]></RESULT>
      </TEST>
      <TEST INDEX="55" NAME="Respect de la casse du nom du type" DESCRIPTION="Les noms du type et de l'espace de noms ne doivent pas varier uniquement au niveau de la casse." EXECUTIONTIME="00h:00m:00s.83ms" OPTIONAL="FALSE">
        <MESSAGES />
        <RESULT><![CDATA[PASS]]></RESULT>
      </TEST>
      <TEST INDEX="54" NAME="Exactitude du nom du type" DESCRIPTION="Seuls des types système peuvent être dans l'espace de noms Windows et aucun titre ne peut être dans l'espace de noms global." EXECUTIONTIME="00h:00m:00s.82ms" OPTIONAL="FALSE">
        <MESSAGES />
        <RESULT><![CDATA[PASS]]></RESULT>
      </TEST>
      <TEST INDEX="58" NAME="Exactitude des métadonnées générales" DESCRIPTION="Les fichiers de métadonnées doivent répondre à diverses exigences afin d'être valides et exacts." EXECUTIONTIME="00h:00m:09s.13ms" OPTIONAL="TRUE">
        <MESSAGES />
        <RESULT><![CDATA[PASS]]></RESULT>
      </TEST>
      <TEST INDEX="53" NAME="Propriétés" DESCRIPTION="Impossible d'utiliser des propriétés d'écriture seule et d'indexeur." EXECUTIONTIME="00h:00m:00s.79ms" OPTIONAL="FALSE">
        <MESSAGES />
        <RESULT><![CDATA[PASS]]></RESULT>
      </TEST>
    </REQUIREMENT>
    <REQUIREMENT NUMBER="25" TITLE="Test d’intégrité du package" RATIONALE="Validation du contenu du package d’application visant à garantir son exactitude.">
      <TEST INDEX="89" NAME="Utilisation des fichiers d'archives" DESCRIPTION="Les packages ne doivent pas contenir de fichiers PE dans des fichiers d'archives." EXECUTIONTIME="00h:00m:00s.83ms" OPTIONAL="TRUE">
        <MESSAGES />
        <RESULT><![CDATA[PASS]]></RESULT>
      </TEST>
      <TEST INDEX="88" NAME="Fichiers exécutables bloqués" DESCRIPTION="Détecte s’il existe des références pour traiter les API de lancement et les fichiers exécutables bloqués" EXECUTIONTIME="00h:00m:01s.14ms" OPTIONAL="TRUE">
        <MESSAGES>
          <MESSAGE TEXT="Le fichier C:\Program Files\WindowsApps\AZERTYGlobal.AZERTYGlobal_0.9.7.1_x64__w9kghr08zmhbg\AZERTY Global.exe contient une référence à une API liée à un « processus de lancement » shell32.dll!ShellExecuteW" />
          <MESSAGE TEXT="Le fichier README.md contient une référence exécutable bloquée à « powershell »." />
        </MESSAGES>
        <RESULT><![CDATA[FAIL]]></RESULT>
      </TEST>
      <TEST INDEX="63" NAME="Fichiers appropriés pour la plateforme" DESCRIPTION="L’application ne doit pas installer de fichiers ne correspondant pas à l’architecture du processeur cible." EXECUTIONTIME="00h:00m:00s.86ms" OPTIONAL="TRUE">
        <MESSAGES />
        <RESULT><![CDATA[PASS]]></RESULT>
      </TEST>
    </REQUIREMENT>
    <REQUIREMENT NUMBER="26" TITLE="Prise en charge de la haute résolution" RATIONALE="L’application doit définir la prise en charge DPI pour que l’apparence de l’interface utilisateur soit cohérente entre de nombreux paramètres d’affichage en haute résolution.">
      <TEST INDEX="92" NAME="DPIAwarenessValidation" DESCRIPTION="Les applications doivent définir la prise en charge de DPI pour que l'affichage de l'interface utilisateur soit cohérent sur un large éventail de paramètres d'affichage en haute résolution." EXECUTIONTIME="00h:00m:00s.90ms" OPTIONAL="FALSE">
        <MESSAGES>
          <MESSAGE TEXT="Impossible de traiter le C:\Program Files\WindowsApps\AZERTYGlobal.AZERTYGlobal_0.9.7.1_x64__w9kghr08zmhbg\AZERTY Global.exe binaire." />
          <MESSAGE TEXT="L'application AZERTYGlobal.AZERTYGlobal_0.9.7.1_x64__w9kghr08zmhbg n'est pas compatible avec DPI." />
        </MESSAGES>
        <RESULT><![CDATA[WARNING]]></RESULT>
      </TEST>
    </REQUIREMENT>
  </REQUIREMENTS>
  <APPLICATIONS>
    <Installed_Programs>
      <Program Name="AZERTYGlobal.AZERTYGlobal" Type="Application" Source="AppxPackage" Publisher="CN=7FD049E3-1C58-42E0-A07F-A9712DE19E38" Version="0.9.7.1" Language="1036" InstallDate="" RootDirPath="C:\Program Files\WindowsApps\AZERTYGlobal.AZERTYGlobal_0.9.7.1_x64__w9kghr08zmhbg" Id="000027e1623591dccf932fdf3e4947825bbd00000c04" HiddenArp="false">
        <Indicators>
          <WindowsStoreAppManifestIndicators>
            <PackageManifest PackageFullName="AZERTYGlobal.AZERTYGlobal_0.9.7.1_x64__w9kghr08zmhbg">
              <Package>
                <Identity Name="AZERTYGlobal.AZERTYGlobal" Publisher="CN=7FD049E3-1C58-42E0-A07F-A9712DE19E38" Version="0.9.7.1" ProcessorArchitecture="x64"></Identity>
                <Properties>
                  <DisplayName>AZERTY Global - Clavier français amélioré</DisplayName>
                  <PublisherDisplayName>AZERTY Global</PublisherDisplayName>
                  <Logo>Assets\StoreLogo.png</Logo>
                  <Description>L'AZERTY corrigé : majuscules accentuées, point direct, symboles dev accessibles, langues étrangères.</Description>
                </Properties>
                <Dependencies>
                  <TargetDeviceFamily Name="Windows.Desktop" MinVersion="10.0.17763.0" MaxVersionTested="10.0.26100.0"></TargetDeviceFamily>
                </Dependencies>
                <Resources>
                  <Resource Language="fr-FR"></Resource>
                  <Resource Language="en-US"></Resource>
                </Resources>
                <Applications>
                  <Application Id="AZERTYGlobal" Executable="AZERTY Global.exe" EntryPoint="Windows.FullTrustApplication">
                    <VisualElements DisplayName="AZERTY Global - Clavier français amélioré" Description="L'AZERTY corrigé : majuscules accentuées, point direct, symboles dev accessibles, langues étrangères." BackgroundColor="#1a1a2e" Square150x150Logo="Assets\Square150x150Logo.png" Square44x44Logo="Assets\Square44x44Logo.png" ForegroundText="light">
                      <DefaultTile Wide310x150Logo="Assets\Wide310x150Logo.png"></DefaultTile>
                    </VisualElements>
                    <Extensions>
                      <Extension Category="windows.startupTask" Executable="AZERTY Global.exe" EntryPoint="Windows.FullTrustApplication">
                        <StartupTask TaskId="AZERTYGlobalStartup" Enabled="false" DisplayName="AZERTY Global"></StartupTask>
                      </Extension>
                    </Extensions>
                  </Application>
                </Applications>
                <Capabilities>
                  <Capability Name="runFullTrust"></Capability>
                </Capabilities>
              </Package>
            </PackageManifest>
            <BundleManifest PackageFamilyName="AZERTYGlobal.AZERTYGlobal_w9kghr08zmhbg">
              <Bundle SchemaVersion="5.0" IgnorableNamespaces="b4 b5">
                <Identity Name="AZERTYGlobal.AZERTYGlobal" Publisher="CN=7FD049E3-1C58-42E0-A07F-A9712DE19E38" Version="0.9.7.1"></Identity>
                <Packages>
                  <Package Type="application" Version="0.9.7.1" Architecture="x64" FileName="AZERTYGlobal-0.9.7.1-x64.msix" Offset="5619030" Size="5662561">
                    <Resources>
                      <Resource Language="fr-FR"></Resource>
                      <Resource Language="en-US"></Resource>
                    </Resources>
                    <Dependencies>
                      <TargetDeviceFamily Name="Windows.Desktop" MinVersion="10.0.17763.0" MaxVersionTested="10.0.26100.0"></TargetDeviceFamily>
                    </Dependencies>
                  </Package>
                  <Package Type="application" Version="0.9.7.1" Architecture="arm64" FileName="AZERTYGlobal-0.9.7.1-arm64.msix" Offset="61" Size="5618886">
                    <Resources>
                      <Resource Language="fr-FR"></Resource>
                      <Resource Language="en-US"></Resource>
                    </Resources>
                    <Dependencies>
                      <TargetDeviceFamily Name="Windows.Desktop" MinVersion="10.0.17763.0" MaxVersionTested="10.0.26100.0"></TargetDeviceFamily>
                    </Dependencies>
                  </Package>
                </Packages>
              </Bundle>
            </BundleManifest>
          </WindowsStoreAppManifestIndicators>
        </Indicators>
        <StaticProperties>
          <Files Id="0000da39a3ee5e6b4b0d3255bfef95601890afd80709">
            <File Id="000077a10960a2b041b667afdb4dfd7157506f5ebef2" Name="AZERTY Global.exe" ProductName="azerty global" CompanyName="azerty global" ProductVersion="0.9.7.1" VerLanguage="0" SwitchBackContext="0" FileVersion="0.9.7.1" OriginalFileName="azerty global.dll" InternalName="azerty global.dll" Size="5087232" SizeOfImage="6205440" PeHeaderHash="010113bddaa73aaf884be3399876b7212fe806815888" PeChecksum="0" CrcChecksum="1581321987" BinProductVersion="0.9.7.1" BinFileVersion="0.9.7.1" FileDescription="azerty global" LegalCopyright="© 2017-2026 antoine olivier — eupl 1.2" LinkDate="05/05/2026 20:35:58" BinaryType="pe64_amd64" LowerCaseLongPath="c:\program files\windowsapps\azertyglobal.azertyglobal_0.9.7.1_x64__w9kghr08zmhbg\azerty global.exe" SigPublisherName="" PeSubsystem="2" PeCharacteristics="34" Sha256="1a5cda5add32d166eb986d4ea5f5c7f2dfb43685b940add3fa4e5ab80f860742" />
            <File Id="0000fc00c5f532590481c360404f35a1a63c9cf05ede" Name="screenshot-5-changements.html" ProductName="" CompanyName="" ProductVersion="" VerLanguage="0" SwitchBackContext="0" FileVersion="" OriginalFileName="" InternalName="" Size="6153" SizeOfImage="0" PeHeaderHash="" PeChecksum="0" CrcChecksum="1978986261" BinProductVersion="" BinFileVersion="" FileDescription="" LegalCopyright="" LinkDate="" BinaryType="data_only" LowerCaseLongPath="c:\program files\windowsapps\azertyglobal.azertyglobal_0.9.7.1_x64__w9kghr08zmhbg\assets\screenshot-5-changements.html" SigPublisherName="" PeSubsystem="0" PeCharacteristics="0" Sha256="7effd44d29a4a4400d2db27081f38da8b93816d00585b4c37dc70fbda83becda" />
            <File Id="0000db6a92b25b5619ff995293ae425ccd12f4dd1663" Name="screenshot-avant-apres.html" ProductName="" CompanyName="" ProductVersion="" VerLanguage="0" SwitchBackContext="0" FileVersion="" OriginalFileName="" InternalName="" Size="5601" SizeOfImage="0" PeHeaderHash="" PeChecksum="0" CrcChecksum="2401121080" BinProductVersion="" BinFileVersion="" FileDescription="" LegalCopyright="" LinkDate="" BinaryType="data_only" LowerCaseLongPath="c:\program files\windowsapps\azertyglobal.azertyglobal_0.9.7.1_x64__w9kghr08zmhbg\assets\screenshot-avant-apres.html" SigPublisherName="" PeSubsystem="0" PeCharacteristics="0" Sha256="4c560185c987ee1442d964cecc735e3f7510ca33b31a7d4d0e66f62df218a350" />
          </Files>
        </StaticProperties>
      </Program>
    </Installed_Programs>
  </APPLICATIONS>
  <DEPENDENCY_INFORMATION>
    <AitStaticAnalysis ProgramId="000027e1623591dccf932fdf3e4947825bbd00000904" AnalysisVersion="1.80" DictionaryVersion="3.7" Type="Package" Id="AZERTYGlobal.AZERTYGlobal_0.9.7.1_x64__w9kghr08zmhbg">
      <AitFile ErrorCode="0" Name="AZERTY Global.exe" Id="000077a10960a2b041b667afdb4dfd7157506f5ebef2">
        <AitCategory Id="Com">
          <AitFeature Name="{00000000-0000-0000-0000-000000000001}" />
          <AitFeature Name="{00000000-0000-0000-0000-000000000012}" />
          <AitFeature Name="{00000000-0000-0000-c000-000000000046}" />
          <AitFeature Name="{00000003-0000-0000-c000-000000000046}" />
          <AitFeature Name="{00000035-0000-0000-c000-000000000046}" />
          <AitFeature Name="{00000036-0000-0000-c000-000000000046}" />
          <AitFeature Name="{00000037-0000-0000-c000-000000000046}" />
          <AitFeature Name="{00000038-0000-0000-c000-000000000046}" />
          <AitFeature Name="{00000146-0000-0000-c000-000000000046}" />
          <AitFeature Name="{000001da-0000-0000-c000-000000000046}" />
          <AitFeature Name="{036d2c08-df29-41af-8aa2-d774be62ba6f}" />
          <AitFeature Name="{0385688e-e3c7-5c5e-a389-5524ede349f1}" />
          <AitFeature Name="{04a2dbf3-df83-116c-0946-0812abf6e07d}" />
          <AitFeature Name="{0a299774-3e4e-fc42-1d9d-72cee105ca57}" />
          <AitFeature Name="{11d3b13a-180e-4789-a8be-7712882893e6}" />
          <AitFeature Name="{1b8e9594-588e-5a07-9e65-0731a4c9a2db}" />
          <AitFeature Name="{1cf2b120-547d-101b-8e65-08002b2bd119}" />
          <AitFeature Name="{1ee770ff-c954-59ca-a754-6199a9be282c}" />
          <AitFeature Name="{28b167d5-1a31-465b-9b25-d5c3ae686c40}" />
          <AitFeature Name="{2af22683-3734-56d0-a60e-688cc85d1619}" />
          <AitFeature Name="{2f2d6c29-5473-5f3e-92e7-96572bb990e2}" />
          <AitFeature Name="{30da92c0-23e8-42a0-ae7c-734a0e5d2782}" />
          <AitFeature Name="{346dd6e7-976e-4bc3-815d-ece243bc0f33}" />
          <AitFeature Name="{3830ad99-d8da-53f3-989b-fc92ad222778}" />
          <AitFeature Name="{38b60434-d67c-523e-9d0e-24d643411073}" />
          <AitFeature Name="{393de7de-6fd0-4c0d-bb71-47244a113e93}" />
          <AitFeature Name="{3c00fd60-2950-5939-a21a-2d12c5a01b8a}" />
          <AitFeature Name="{44a9796f-723e-4fdf-a218-033e75b0c084}" />
          <AitFeature Name="{48f6a69e-8465-57ae-9400-9764087f65ad}" />
          <AitFeature Name="{4bd682dd-7554-40e9-9a9b-82654ede7e62}" />
          <AitFeature Name="{4cf68d33-e3f2-4964-b85e-945b4f7e2f21}" />
          <AitFeature Name="{4dda9e24-e69f-5c6a-a0a6-93427365af2a}" />
          <AitFeature Name="{50f19c16-0a22-4d8e-a089-1ea9951657d2}" />
          <AitFeature Name="{513ef3af-e784-5325-a91e-97c2b8111cf3}" />
          <AitFeature Name="{548cefbd-bc8a-5fa0-8df2-957440fc8bf4}" />
          <AitFeature Name="{5541d8a7-497c-5aa4-86fc-7713adbf2a2c}" />
          <AitFeature Name="{5746e5c4-5b97-424c-b620-2822915734dd}" />
          <AitFeature Name="{5ab7d2c3-6b62-5e71-a4b6-2d49c4f238fd}" />
          <AitFeature Name="{604d0c4c-91de-5c2a-935f-362f13eaf800}" />
          <AitFeature Name="{61723086-8e53-5276-9f36-2a4bb93e2b75}" />
          <AitFeature Name="{6624a2dd-83f7-519c-9d55-bb1f6560456b}" />
          <AitFeature Name="{6755e376-53bb-568b-a11d-17239868309e}" />
          <AitFeature Name="{6ab1ea83-cb41-5f99-92cc-23bd4336a1fb}" />
          <AitFeature Name="{6dcc9c03-e0c7-4eee-8ea9-37e3406eeb1c}" />
          <AitFeature Name="{6e333271-2e2a-5955-8790-836c76ee53b6}" />
          <AitFeature Name="{6ec9e41b-6709-5647-9918-a1270110fc4e}" />
          <AitFeature Name="{719cc2ba-3e76-5def-9f1a-38d85a145ea8}" />
          <AitFeature Name="{76358cfd-2cbd-525b-a49e-90ee18247b71}" />
          <AitFeature Name="{7c925755-3e48-42b4-8677-76372267033f}" />
          <AitFeature Name="{7d50f649-632c-51f9-849a-ee49428933ea}" />
          <AitFeature Name="{80423f11-054f-5eac-afd3-63b6ce15e77b}" />
          <AitFeature Name="{82ba7092-4c88-427d-a7bc-16dd93feb67e}" />
          <AitFeature Name="{84f14c22-a00a-5272-8d3d-82112e66df00}" />
          <AitFeature Name="{912f8fd7-adc0-5d60-a896-7ed76089cc5b}" />
          <AitFeature Name="{94ea2b94-e9cc-49e0-c0ff-ee64ca8f5b90}" />
          <AitFeature Name="{96369f54-8eb6-48f0-abce-c1b211e627c3}" />
          <AitFeature Name="{97374b68-eb87-56cc-b18e-27ef0f9cfc0c}" />
          <AitFeature Name="{9cd7a84f-0c80-59c5-b44e-977841bb43d9}" />
          <AitFeature Name="{a4095aab-eb7d-5782-8fad-1609dea249ad}" />
          <AitFeature Name="{a5e843c9-ed20-5339-8f8d-9fe404cf3654}" />
          <AitFeature Name="{a6d080a5-b087-5bc2-9a9f-5cd687b4d1f7}" />
          <AitFeature Name="{ad73197d-2cfa-57a6-8993-9fac40feb791}" />
          <AitFeature Name="{af86e2e0-b12d-4c6a-9c5a-d7aa65101e90}" />
          <AitFeature Name="{b27004bb-c014-5dce-9a21-799c5a3c1461}" />
          <AitFeature Name="{b30c3e3a-df8d-44a5-9a38-7ac0d08ce63d}" />
          <AitFeature Name="{c50898f6-c536-5f47-8583-8b2c2438a13b}" />
          <AitFeature Name="{ca10b37c-f382-4591-8557-5e24965279b0}" />
          <AitFeature Name="{cf75d69c-f2f4-486b-b302-bb4c09baebfa}" />
          <AitFeature Name="{d301f253-e0a3-5d2b-9a41-a4d62bec4623}" />
          <AitFeature Name="{dacbffdc-68ef-5fd0-b657-782d0ac9807e}" />
          <AitFeature Name="{df0b3d60-548f-101b-8e65-08002b2bd119}" />
          <AitFeature Name="{e5198cc8-2873-55f5-b0a1-84ff9e4aad62}" />
          <AitFeature Name="{e5af3542-ca67-4081-995b-709dd13792df}" />
          <AitFeature Name="{e8e72666-48cc-593f-ba85-2663496956e3}" />
          <AitFeature Name="{ee5b60bd-a148-41a7-b26e-e8b88a1e62f8}" />
          <AitFeature Name="{eecf9838-c1c2-5b4a-976f-cec261ae1d55}" />
          <AitFeature Name="{f75c23c8-b5f2-4f6c-88dd-36cb1d599d17}" />
          <AitFeature Name="{fb393ef3-bbac-5bd5-9144-84f23576f415}" />
          <AitFeature Name="{fd416dfb-2a07-52eb-aae3-dfce14116c05}" />
        </AitCategory>
        <AitCategory Id="WinRtCom">
          <AitFeature Name="{00000036-0000-0000-c000-000000000046}" />
          <AitFeature Name="{036d2c08-df29-41af-8aa2-d774be62ba6f}" />
          <AitFeature Name="{28b167d5-1a31-465b-9b25-d5c3ae686c40}" />
          <AitFeature Name="{30da92c0-23e8-42a0-ae7c-734a0e5d2782}" />
          <AitFeature Name="{346dd6e7-976e-4bc3-815d-ece243bc0f33}" />
          <AitFeature Name="{393de7de-6fd0-4c0d-bb71-47244a113e93}" />
          <AitFeature Name="{44a9796f-723e-4fdf-a218-033e75b0c084}" />
          <AitFeature Name="{4bd682dd-7554-40e9-9a9b-82654ede7e62}" />
          <AitFeature Name="{4cf68d33-e3f2-4964-b85e-945b4f7e2f21}" />
          <AitFeature Name="{50f19c16-0a22-4d8e-a089-1ea9951657d2}" />
          <AitFeature Name="{6dcc9c03-e0c7-4eee-8ea9-37e3406eeb1c}" />
          <AitFeature Name="{7c925755-3e48-42b4-8677-76372267033f}" />
          <AitFeature Name="{96369f54-8eb6-48f0-abce-c1b211e627c3}" />
          <AitFeature Name="{b30c3e3a-df8d-44a5-9a38-7ac0d08ce63d}" />
          <AitFeature Name="{ca10b37c-f382-4591-8557-5e24965279b0}" />
          <AitFeature Name="{cf75d69c-f2f4-486b-b302-bb4c09baebfa}" />
          <AitFeature Name="{e5af3542-ca67-4081-995b-709dd13792df}" />
          <AitFeature Name="{ee5b60bd-a148-41a7-b26e-e8b88a1e62f8}" />
          <AitFeature Name="{f75c23c8-b5f2-4f6c-88dd-36cb1d599d17}" />
        </AitCategory>
        <AitCategory Id="ApiStatic">
          <AitFeature Name="api-ms-win-crt-locale-l1-1-0.dll!_configthreadlocale" />
          <AitFeature Name="api-ms-win-crt-runtime-l1-1-0.dll!__p___argc" />
          <AitFeature Name="api-ms-win-crt-runtime-l1-1-0.dll!__p___wargv" />
          <AitFeature Name="api-ms-win-crt-runtime-l1-1-0.dll!_c_exit" />
          <AitFeature Name="api-ms-win-crt-runtime-l1-1-0.dll!_cexit" />
          <AitFeature Name="api-ms-win-crt-runtime-l1-1-0.dll!_configure_wide_argv" />
          <AitFeature Name="api-ms-win-crt-runtime-l1-1-0.dll!_crt_atexit" />
          <AitFeature Name="api-ms-win-crt-runtime-l1-1-0.dll!_exit" />
          <AitFeature Name="api-ms-win-crt-runtime-l1-1-0.dll!_get_initial_wide_environment" />
          <AitFeature Name="api-ms-win-crt-runtime-l1-1-0.dll!_initialize_onexit_table" />
          <AitFeature Name="api-ms-win-crt-runtime-l1-1-0.dll!_initialize_wide_environment" />
          <AitFeature Name="api-ms-win-crt-runtime-l1-1-0.dll!_initterm" />
          <AitFeature Name="api-ms-win-crt-runtime-l1-1-0.dll!_initterm_e" />
          <AitFeature Name="api-ms-win-crt-runtime-l1-1-0.dll!_register_onexit_function" />
          <AitFeature Name="api-ms-win-crt-runtime-l1-1-0.dll!_register_thread_local_exe_atexit_callback" />
          <AitFeature Name="api-ms-win-crt-runtime-l1-1-0.dll!_seh_filter_exe" />
          <AitFeature Name="api-ms-win-crt-runtime-l1-1-0.dll!_set_app_type" />
          <AitFeature Name="api-ms-win-crt-runtime-l1-1-0.dll!abort" />
          <AitFeature Name="api-ms-win-crt-runtime-l1-1-0.dll!exit" />
          <AitFeature Name="api-ms-win-crt-runtime-l1-1-0.dll!terminate" />
          <AitFeature Name="api-ms-win-crt-string-l1-1-0.dll!_stricmp" />
          <AitFeature Name="api-ms-win-crt-string-l1-1-0.dll!strcmp" />
          <AitFeature Name="api-ms-win-crt-string-l1-1-0.dll!strcpy_s" />
          <AitFeature Name="api-ms-win-crt-string-l1-1-0.dll!strlen" />
          <AitFeature Name="api-ms-win-crt-string-l1-1-0.dll!strncpy_s" />
          <AitFeature Name="api-ms-win-crt-string-l1-1-0.dll!wcsncmp" />
          <AitFeature Name="api-ms-win-crt-math-l1-1-0.dll!__setusermatherr" />
          <AitFeature Name="api-ms-win-crt-math-l1-1-0.dll!ceil" />
          <AitFeature Name="api-ms-win-crt-math-l1-1-0.dll!cos" />
          <AitFeature Name="api-ms-win-crt-math-l1-1-0.dll!floor" />
          <AitFeature Name="api-ms-win-crt-math-l1-1-0.dll!modf" />
          <AitFeature Name="api-ms-win-crt-math-l1-1-0.dll!pow" />
          <AitFeature Name="api-ms-win-crt-math-l1-1-0.dll!sin" />
          <AitFeature Name="api-ms-win-crt-math-l1-1-0.dll!tan" />
          <AitFeature Name="api-ms-win-crt-stdio-l1-1-0.dll!__acrt_iob_func" />
          <AitFeature Name="api-ms-win-crt-stdio-l1-1-0.dll!__p__commode" />
          <AitFeature Name="api-ms-win-crt-stdio-l1-1-0.dll!__stdio_common_vfprintf" />
          <AitFeature Name="api-ms-win-crt-stdio-l1-1-0.dll!__stdio_common_vsprintf_s" />
          <AitFeature Name="api-ms-win-crt-stdio-l1-1-0.dll!__stdio_common_vsscanf" />
          <AitFeature Name="api-ms-win-crt-stdio-l1-1-0.dll!_set_fmode" />
          <AitFeature Name="api-ms-win-crt-heap-l1-1-0.dll!_callnewh" />
          <AitFeature Name="api-ms-win-crt-heap-l1-1-0.dll!_set_new_mode" />
          <AitFeature Name="api-ms-win-crt-heap-l1-1-0.dll!calloc" />
          <AitFeature Name="api-ms-win-crt-heap-l1-1-0.dll!free" />
          <AitFeature Name="api-ms-win-crt-heap-l1-1-0.dll!malloc" />
          <AitFeature Name="api-ms-win-crt-heap-l1-1-0.dll!realloc" />
          <AitFeature Name="api-ms-win-crt-convert-l1-1-0.dll!strtoull" />
          <AitFeature Name="ole32.dll!CoCreateGuid" />
          <AitFeature Name="ole32.dll!CoCreateInstance" />
          <AitFeature Name="ole32.dll!CoGetApartmentType" />
          <AitFeature Name="ole32.dll!CoGetContextToken" />
          <AitFeature Name="ole32.dll!CoInitializeEx" />
          <AitFeature Name="ole32.dll!CoTaskMemAlloc" />
          <AitFeature Name="ole32.dll!CoTaskMemFree" />
          <AitFeature Name="ole32.dll!CoUninitialize" />
          <AitFeature Name="ole32.dll!CoWaitForMultipleHandles" />
          <AitFeature Name="ole32.dll!CreateStreamOnHGlobal" />
          <AitFeature Name="advapi32.dll!AdjustTokenPrivileges" />
          <AitFeature Name="advapi32.dll!LookupPrivilegeValueW" />
          <AitFeature Name="advapi32.dll!OpenProcessToken" />
          <AitFeature Name="advapi32.dll!RegCloseKey" />
          <AitFeature Name="advapi32.dll!RegEnumKeyExW" />
          <AitFeature Name="advapi32.dll!RegEnumValueW" />
          <AitFeature Name="advapi32.dll!RegOpenKeyExW" />
          <AitFeature Name="advapi32.dll!RegQueryValueExW" />
          <AitFeature Name="kernel32.dll!AddVectoredExceptionHandler" />
          <AitFeature Name="kernel32.dll!CancelThreadpoolIo" />
          <AitFeature Name="kernel32.dll!CloseHandle" />
          <AitFeature Name="kernel32.dll!CloseThreadpoolIo" />
          <AitFeature Name="kernel32.dll!CloseThreadpoolWork" />
          <AitFeature Name="kernel32.dll!CompareStringEx" />
          <AitFeature Name="kernel32.dll!CompareStringOrdinal" />
          <AitFeature Name="kernel32.dll!CopyFileExW" />
          <AitFeature Name="kernel32.dll!CreateDirectoryW" />
          <AitFeature Name="kernel32.dll!CreateEventExW" />
          <AitFeature Name="kernel32.dll!CreateEventW" />
          <AitFeature Name="kernel32.dll!CreateFileW" />
          <AitFeature Name="kernel32.dll!CreateIoCompletionPort" />
          <AitFeature Name="kernel32.dll!CreateMutexExW" />
          <AitFeature Name="kernel32.dll!CreateThread" />
          <AitFeature Name="kernel32.dll!CreateThreadpoolIo" />
          <AitFeature Name="kernel32.dll!CreateThreadpoolTimer" />
          <AitFeature Name="kernel32.dll!CreateThreadpoolWork" />
          <AitFeature Name="kernel32.dll!DebugBreak" />
          <AitFeature Name="kernel32.dll!DeleteCriticalSection" />
          <AitFeature Name="kernel32.dll!DeleteFileW" />
          <AitFeature Name="kernel32.dll!DeleteVolumeMountPointW" />
          <AitFeature Name="kernel32.dll!DeviceIoControl" />
          <AitFeature Name="kernel32.dll!DuplicateHandle" />
          <AitFeature Name="kernel32.dll!EncodePointer" />
          <AitFeature Name="kernel32.dll!EnterCriticalSection" />
          <AitFeature Name="kernel32.dll!EnumCalendarInfoExEx" />
          <AitFeature Name="kernel32.dll!EnumTimeFormatsEx" />
          <AitFeature Name="kernel32.dll!ExpandEnvironmentStringsW" />
          <AitFeature Name="kernel32.dll!FileTimeToSystemTime" />
          <AitFeature Name="kernel32.dll!FindClose" />
          <AitFeature Name="kernel32.dll!FindFirstFileExW" />
          <AitFeature Name="kernel32.dll!FindNLSStringEx" />
          <AitFeature Name="kernel32.dll!FindNextFileW" />
          <AitFeature Name="kernel32.dll!FindStringOrdinal" />
          <AitFeature Name="kernel32.dll!FlsAlloc" />
          <AitFeature Name="kernel32.dll!FlsGetValue" />
          <AitFeature Name="kernel32.dll!FlsSetValue" />
          <AitFeature Name="kernel32.dll!FlushFileBuffers" />
          <AitFeature Name="kernel32.dll!FlushInstructionCache" />
          <AitFeature Name="kernel32.dll!FlushProcessWriteBuffers" />
          <AitFeature Name="kernel32.dll!FormatMessageW" />
          <AitFeature Name="kernel32.dll!FreeLibrary" />
          <AitFeature Name="kernel32.dll!GetCPInfo" />
          <AitFeature Name="kernel32.dll!GetCalendarInfoEx" />
          <AitFeature Name="kernel32.dll!GetConsoleOutputCP" />
          <AitFeature Name="kernel32.dll!GetCurrentProcess" />
          <AitFeature Name="kernel32.dll!GetCurrentProcessId" />
          <AitFeature Name="kernel32.dll!GetCurrentProcessorNumberEx" />
          <AitFeature Name="kernel32.dll!GetCurrentThread" />
          <AitFeature Name="kernel32.dll!GetCurrentThreadId" />
          <AitFeature Name="kernel32.dll!GetDynamicTimeZoneInformation" />
          <AitFeature Name="kernel32.dll!GetEnabledXStateFeatures" />
          <AitFeature Name="kernel32.dll!GetEnvironmentVariableW" />
          <AitFeature Name="kernel32.dll!GetFileAttributesExW" />
          <AitFeature Name="kernel32.dll!GetFileInformationByHandleEx" />
          <AitFeature Name="kernel32.dll!GetFileType" />
          <AitFeature Name="kernel32.dll!GetFullPathNameW" />
          <AitFeature Name="kernel32.dll!GetLargePageMinimum" />
          <AitFeature Name="kernel32.dll!GetLastError" />
          <AitFeature Name="kernel32.dll!GetLocaleInfoEx" />
          <AitFeature Name="kernel32.dll!GetLogicalProcessorInformation" />
          <AitFeature Name="kernel32.dll!GetLogicalProcessorInformationEx" />
          <AitFeature Name="kernel32.dll!GetLongPathNameW" />
          <AitFeature Name="kernel32.dll!GetModuleFileNameW" />
          <AitFeature Name="kernel32.dll!GetModuleHandleExW" />
          <AitFeature Name="kernel32.dll!GetModuleHandleW" />
          <AitFeature Name="kernel32.dll!GetNumaHighestNodeNumber" />
          <AitFeature Name="kernel32.dll!GetOverlappedResult" />
          <AitFeature Name="kernel32.dll!GetProcAddress" />
          <AitFeature Name="kernel32.dll!GetProcessAffinityMask" />
          <AitFeature Name="kernel32.dll!GetProcessGroupAffinity" />
          <AitFeature Name="kernel32.dll!GetStdHandle" />
          <AitFeature Name="kernel32.dll!GetSystemDirectoryW" />
          <AitFeature Name="kernel32.dll!GetSystemInfo" />
          <AitFeature Name="kernel32.dll!GetSystemTime" />
          <AitFeature Name="kernel32.dll!GetSystemTimeAsFileTime" />
          <AitFeature Name="kernel32.dll!GetThreadContext" />
          <AitFeature Name="kernel32.dll!GetThreadPriority" />
          <AitFeature Name="kernel32.dll!GetTickCount64" />
          <AitFeature Name="kernel32.dll!GetTimeZoneInformation" />
          <AitFeature Name="kernel32.dll!GetUserPreferredUILanguages" />
          <AitFeature Name="kernel32.dll!GlobalAlloc" />
          <AitFeature Name="kernel32.dll!GlobalFree" />
          <AitFeature Name="kernel32.dll!GlobalMemoryStatusEx" />
          <AitFeature Name="kernel32.dll!InitializeConditionVariable" />
          <AitFeature Name="kernel32.dll!InitializeContext" />
          <AitFeature Name="kernel32.dll!InitializeCriticalSection" />
          <AitFeature Name="kernel32.dll!InitializeCriticalSectionAndSpinCount" />
          <AitFeature Name="kernel32.dll!InitializeCriticalSectionEx" />
          <AitFeature Name="kernel32.dll!InitializeSListHead" />
          <AitFeature Name="kernel32.dll!IsDebuggerPresent" />
          <AitFeature Name="kernel32.dll!IsProcessInJob" />
          <AitFeature Name="kernel32.dll!IsProcessorFeaturePresent" />
          <AitFeature Name="kernel32.dll!K32GetProcessMemoryInfo" />
          <AitFeature Name="kernel32.dll!LCMapStringEx" />
          <AitFeature Name="kernel32.dll!LeaveCriticalSection" />
          <AitFeature Name="kernel32.dll!LoadLibraryExW" />
          <AitFeature Name="kernel32.dll!LocalAlloc" />
          <AitFeature Name="kernel32.dll!LocalFree" />
          <AitFeature Name="kernel32.dll!LocaleNameToLCID" />
          <AitFeature Name="kernel32.dll!MoveFileExW" />
          <AitFeature Name="kernel32.dll!MultiByteToWideChar" />
          <AitFeature Name="kernel32.dll!OpenProcess" />
          <AitFeature Name="kernel32.dll!QueryInformationJobObject" />
          <AitFeature Name="kernel32.dll!QueryPerformanceCounter" />
          <AitFeature Name="kernel32.dll!QueryPerformanceFrequency" />
          <AitFeature Name="kernel32.dll!QueryUnbiasedInterruptTime" />
          <AitFeature Name="kernel32.dll!RaiseException" />
          <AitFeature Name="kernel32.dll!RaiseFailFastException" />
          <AitFeature Name="kernel32.dll!ReadFile" />
          <AitFeature Name="kernel32.dll!RemoveDirectoryW" />
          <AitFeature Name="kernel32.dll!ReplaceFileW" />
          <AitFeature Name="kernel32.dll!ResetEvent" />
          <AitFeature Name="kernel32.dll!ResolveLocaleName" />
          <AitFeature Name="kernel32.dll!ResumeThread" />
          <AitFeature Name="kernel32.dll!RtlCaptureContext" />
          <AitFeature Name="kernel32.dll!RtlLookupFunctionEntry" />
          <AitFeature Name="kernel32.dll!RtlPcToFileHeader" />
          <AitFeature Name="kernel32.dll!RtlRestoreContext" />
          <AitFeature Name="kernel32.dll!RtlUnwindEx" />
          <AitFeature Name="kernel32.dll!RtlVirtualUnwind" />
          <AitFeature Name="kernel32.dll!SetEvent" />
          <AitFeature Name="kernel32.dll!SetFileInformationByHandle" />
          <AitFeature Name="kernel32.dll!SetLastError" />
          <AitFeature Name="kernel32.dll!SetThreadContext" />
          <AitFeature Name="kernel32.dll!SetThreadErrorMode" />
          <AitFeature Name="kernel32.dll!SetThreadPriority" />
          <AitFeature Name="kernel32.dll!SetThreadpoolTimer" />
          <AitFeature Name="kernel32.dll!SetUnhandledExceptionFilter" />
          <AitFeature Name="kernel32.dll!SetXStateFeaturesMask" />
          <AitFeature Name="kernel32.dll!Sleep" />
          <AitFeature Name="kernel32.dll!SleepConditionVariableCS" />
          <AitFeature Name="kernel32.dll!SleepEx" />
          <AitFeature Name="kernel32.dll!StartThreadpoolIo" />
          <AitFeature Name="kernel32.dll!SubmitThreadpoolWork" />
          <AitFeature Name="kernel32.dll!SuspendThread" />
          <AitFeature Name="kernel32.dll!SwitchToThread" />
          <AitFeature Name="kernel32.dll!SystemTimeToFileTime" />
          <AitFeature Name="kernel32.dll!TerminateProcess" />
          <AitFeature Name="kernel32.dll!TlsAlloc" />
          <AitFeature Name="kernel32.dll!TlsFree" />
          <AitFeature Name="kernel32.dll!TlsGetValue" />
          <AitFeature Name="kernel32.dll!TlsSetValue" />
          <AitFeature Name="kernel32.dll!TzSpecificLocalTimeToSystemTime" />
          <AitFeature Name="kernel32.dll!UnhandledExceptionFilter" />
          <AitFeature Name="kernel32.dll!VirtualAlloc" />
          <AitFeature Name="kernel32.dll!VirtualAllocExNuma" />
          <AitFeature Name="kernel32.dll!VirtualFree" />
          <AitFeature Name="kernel32.dll!VirtualProtect" />
          <AitFeature Name="kernel32.dll!VirtualQuery" />
          <AitFeature Name="kernel32.dll!VirtualUnlock" />
          <AitFeature Name="kernel32.dll!WaitForMultipleObjectsEx" />
          <AitFeature Name="kernel32.dll!WaitForSingleObject" />
          <AitFeature Name="kernel32.dll!WaitForSingleObjectEx" />
          <AitFeature Name="kernel32.dll!WakeConditionVariable" />
          <AitFeature Name="kernel32.dll!WideCharToMultiByte" />
          <AitFeature Name="kernel32.dll!WriteFile" />
          <AitFeature Name="user32.dll!LoadStringW" />
          <AitFeature Name="oleaut32.dll!201" />
          <AitFeature Name="oleaut32.dll!4" />
          <AitFeature Name="oleaut32.dll!6" />
          <AitFeature Name="oleaut32.dll!SetErrorInfo" />
          <AitFeature Name="oleaut32.dll!SysAllocStringLen" />
          <AitFeature Name="oleaut32.dll!SysFreeString" />
          <AitFeature Name="bcrypt.dll!BCryptCloseAlgorithmProvider" />
          <AitFeature Name="bcrypt.dll!BCryptCreateHash" />
          <AitFeature Name="bcrypt.dll!BCryptDestroyHash" />
          <AitFeature Name="bcrypt.dll!BCryptFinishHash" />
          <AitFeature Name="bcrypt.dll!BCryptGenRandom" />
          <AitFeature Name="bcrypt.dll!BCryptGetProperty" />
          <AitFeature Name="bcrypt.dll!BCryptHashData" />
          <AitFeature Name="bcrypt.dll!BCryptOpenAlgorithmProvider" />
        </AitCategory>
        <AitCategory Id="ApiDynamic">
          <AitFeature Name="ole32.dll!CoCreateFreeThreadedMarshaler" />
          <AitFeature Name="ole32.dll!CoDecrementMTAUsage" />
          <AitFeature Name="ole32.dll!CoGetObjectContext" />
          <AitFeature Name="ole32.dll!CoIncrementMTAUsage" />
          <AitFeature Name="ole32.dll!RoGetAgileReference" />
          <AitFeature Name="msimg32.dll!AlphaBlend" />
          <AitFeature Name="gdi32.dll!BitBlt" />
          <AitFeature Name="gdi32.dll!CreateBitmap" />
          <AitFeature Name="gdi32.dll!CreateCompatibleBitmap" />
          <AitFeature Name="gdi32.dll!CreateCompatibleDC" />
          <AitFeature Name="gdi32.dll!CreateFontW" />
          <AitFeature Name="gdi32.dll!CreatePen" />
          <AitFeature Name="gdi32.dll!CreateSolidBrush" />
          <AitFeature Name="gdi32.dll!DeleteDC" />
          <AitFeature Name="gdi32.dll!DeleteObject" />
          <AitFeature Name="gdi32.dll!Ellipse" />
          <AitFeature Name="gdi32.dll!GetDeviceCaps" />
          <AitFeature Name="gdi32.dll!GetStockObject" />
          <AitFeature Name="gdi32.dll!LineTo" />
          <AitFeature Name="gdi32.dll!MoveToEx" />
          <AitFeature Name="gdi32.dll!Polygon" />
          <AitFeature Name="gdi32.dll!RoundRect" />
          <AitFeature Name="gdi32.dll!SelectObject" />
          <AitFeature Name="gdi32.dll!SetBkColor" />
          <AitFeature Name="gdi32.dll!SetBkMode" />
          <AitFeature Name="gdi32.dll!SetTextColor" />
          <AitFeature Name="kernel32.dll!FlsFree" />
          <AitFeature Name="kernel32.dll!GetCurrentPackageFullName" />
          <AitFeature Name="kernel32.dll!GlobalLock" />
          <AitFeature Name="kernel32.dll!GlobalUnlock" />
          <AitFeature Name="kernel32.dll!IdnToAscii" />
          <AitFeature Name="kernel32.dll!IdnToUnicode" />
          <AitFeature Name="kernel32.dll!InitializeContext2" />
          <AitFeature Name="kernel32.dll!NormalizeString" />
          <AitFeature Name="kernel32.dll!QueueUserAPC2" />
          <AitFeature Name="shell32.dll!SHGetKnownFolderPath" />
          <AitFeature Name="shell32.dll!ShellExecuteW" />
          <AitFeature Name="shell32.dll!Shell_NotifyIconW" />
          <AitFeature Name="comctl32.dll!DefSubclassProc" />
          <AitFeature Name="comctl32.dll!RemoveWindowSubclass" />
          <AitFeature Name="comctl32.dll!SetWindowSubclass" />
          <AitFeature Name="user32.dll!AdjustWindowRectEx" />
          <AitFeature Name="user32.dll!AppendMenuW" />
          <AitFeature Name="user32.dll!AttachThreadInput" />
          <AitFeature Name="user32.dll!BeginPaint" />
          <AitFeature Name="user32.dll!CallNextHookEx" />
          <AitFeature Name="user32.dll!CheckMenuRadioItem" />
          <AitFeature Name="user32.dll!CloseClipboard" />
          <AitFeature Name="user32.dll!CreateIconIndirect" />
          <AitFeature Name="user32.dll!CreatePopupMenu" />
          <AitFeature Name="user32.dll!CreateWindowExW" />
          <AitFeature Name="user32.dll!DefWindowProcW" />
          <AitFeature Name="user32.dll!DestroyIcon" />
          <AitFeature Name="user32.dll!DestroyMenu" />
          <AitFeature Name="user32.dll!DestroyWindow" />
          <AitFeature Name="user32.dll!DispatchMessageW" />
          <AitFeature Name="user32.dll!DrawTextW" />
          <AitFeature Name="user32.dll!EmptyClipboard" />
          <AitFeature Name="user32.dll!EnableWindow" />
          <AitFeature Name="user32.dll!EndPaint" />
          <AitFeature Name="user32.dll!FillRect" />
          <AitFeature Name="user32.dll!GetAsyncKeyState" />
          <AitFeature Name="user32.dll!GetClientRect" />
          <AitFeature Name="user32.dll!GetCursorPos" />
          <AitFeature Name="user32.dll!GetDC" />
          <AitFeature Name="user32.dll!GetDlgCtrlID" />
          <AitFeature Name="user32.dll!GetDoubleClickTime" />
          <AitFeature Name="user32.dll!GetDpiForWindow" />
          <AitFeature Name="user32.dll!GetFocus" />
          <AitFeature Name="user32.dll!GetForegroundWindow" />
          <AitFeature Name="user32.dll!GetKeyState" />
          <AitFeature Name="user32.dll!GetKeyboardLayout" />
          <AitFeature Name="user32.dll!GetMessageW" />
          <AitFeature Name="user32.dll!GetSystemMetrics" />
          <AitFeature Name="user32.dll!GetWindowRect" />
          <AitFeature Name="user32.dll!GetWindowThreadProcessId" />
          <AitFeature Name="user32.dll!InvalidateRect" />
          <AitFeature Name="user32.dll!IsWindowVisible" />
          <AitFeature Name="user32.dll!KillTimer" />
          <AitFeature Name="user32.dll!LoadCursorW" />
          <AitFeature Name="user32.dll!MapVirtualKeyExW" />
          <AitFeature Name="user32.dll!MapVirtualKeyW" />
          <AitFeature Name="user32.dll!MessageBoxW" />
          <AitFeature Name="user32.dll!MonitorFromPoint" />
          <AitFeature Name="user32.dll!MonitorFromWindow" />
          <AitFeature Name="user32.dll!MoveWindow" />
          <AitFeature Name="user32.dll!OpenClipboard" />
          <AitFeature Name="user32.dll!PostMessageW" />
          <AitFeature Name="user32.dll!PostQuitMessage" />
          <AitFeature Name="user32.dll!RegisterClassExW" />
          <AitFeature Name="user32.dll!RegisterWindowMessageW" />
          <AitFeature Name="user32.dll!ReleaseDC" />
          <AitFeature Name="user32.dll!SendInput" />
          <AitFeature Name="user32.dll!SendMessageW" />
          <AitFeature Name="user32.dll!SetClipboardData" />
          <AitFeature Name="user32.dll!SetCursor" />
          <AitFeature Name="user32.dll!SetFocus" />
          <AitFeature Name="user32.dll!SetForegroundWindow" />
          <AitFeature Name="user32.dll!SetLayeredWindowAttributes" />
          <AitFeature Name="user32.dll!SetProcessDPIAware" />
          <AitFeature Name="user32.dll!SetProcessDpiAwarenessContext" />
          <AitFeature Name="user32.dll!SetTimer" />
          <AitFeature Name="user32.dll!SetWinEventHook" />
          <AitFeature Name="user32.dll!SetWindowPos" />
          <AitFeature Name="user32.dll!SetWindowTextW" />
          <AitFeature Name="user32.dll!ShowWindow" />
          <AitFeature Name="user32.dll!ToUnicode" />
          <AitFeature Name="user32.dll!ToUnicodeEx" />
          <AitFeature Name="user32.dll!TrackMouseEvent" />
          <AitFeature Name="user32.dll!TrackPopupMenuEx" />
          <AitFeature Name="user32.dll!TranslateMessage" />
          <AitFeature Name="user32.dll!UnhookWinEvent" />
          <AitFeature Name="user32.dll!UnhookWindowsHookEx" />
          <AitFeature Name="user32.dll!UnregisterClassW" />
          <AitFeature Name="user32.dll!VkKeyScanExW" />
          <AitFeature Name="user32.dll!VkKeyScanW" />
          <AitFeature Name="icuuc.dll!u_strlen" />
          <AitFeature Name="dwmapi.dll!DwmSetWindowAttribute" />
          <AitFeature Name="psapi.dll!EnumProcessModulesEx" />
          <AitFeature Name="psapi.dll!GetModuleFileNameExW" />
          <AitFeature Name="ntdll.dll!NtCreateFile" />
          <AitFeature Name="ntdll.dll!NtQueryDirectoryFile" />
          <AitFeature Name="ntdll.dll!NtQueryInformationFile" />
          <AitFeature Name="ntdll.dll!NtQuerySystemInformation" />
          <AitFeature Name="ntdll.dll!RtlGetVersion" />
          <AitFeature Name="ntdll.dll!RtlNtStatusToDosError" />
          <AitFeature Name="gdiplus.dll!GdipCreateBitmapFromScan0" />
          <AitFeature Name="gdiplus.dll!GdipCreateBitmapFromStream" />
          <AitFeature Name="gdiplus.dll!GdipCreateFromHDC" />
          <AitFeature Name="gdiplus.dll!GdipCreateHBITMAPFromBitmap" />
          <AitFeature Name="gdiplus.dll!GdipDeleteGraphics" />
          <AitFeature Name="gdiplus.dll!GdipDisposeImage" />
          <AitFeature Name="gdiplus.dll!GdipDrawImageRectI" />
          <AitFeature Name="gdiplus.dll!GdipGetImageGraphicsContext" />
          <AitFeature Name="gdiplus.dll!GdipSetInterpolationMode" />
          <AitFeature Name="gdiplus.dll!GdipSetSmoothingMode" />
          <AitFeature Name="gdiplus.dll!GdipSetTextRenderingHint" />
          <AitFeature Name="gdiplus.dll!GdiplusShutdown" />
          <AitFeature Name="gdiplus.dll!GdiplusStartup" />
          <AitFeature Name="bcrypt.dll!BCryptHash" />
          <AitFeature Name="normaliz.dll!IdnToAscii" />
          <AitFeature Name="normaliz.dll!IdnToUnicode" />
          <AitFeature Name="normaliz.dll!NormalizeString" />
        </AitCategory>
        <AitCategory Id="WRTClassFromSearch">
          <AitFeature Name="Windows.Foundation.IReference`1" />
        </AitCategory>
      </AitFile>
      <AitFile ErrorCode="0" Name="screenshot-avant-apres.html" Id="0000db6a92b25b5619ff995293ae425ccd12f4dd1663" />
      <AitFile ErrorCode="0" Name="screenshot-5-changements.html" Id="0000fc00c5f532590481c360404f35a1a63c9cf05ede" />
    </AitStaticAnalysis>
  </DEPENDENCY_INFORMATION>
</REPORT>